README.rst
setup.py
aligo/__init__.py
aligo/client.py
aligo/decorator.py
aligo/exc.py
aligo_rest_client.egg-info/PKG-INFO
aligo_rest_client.egg-info/SOURCES.txt
aligo_rest_client.egg-info/dependency_links.txt
aligo_rest_client.egg-info/requires.txt
aligo_rest_client.egg-info/top_level.txt