Metadata-Version: 1.1
Name: aligo-rest-client
Version: 0.0.2
Summary: Restful client for `Aligo` of SMS service in korea
Home-page: https://github.com/james-song/aligo-rest-client-python
Author: RakGyu Song
Author-email: reeoss@gmail.com
License: MIT License
Platform: UNKNOWN
Classifier: Environment :: Web Environment
Classifier: Intended Audience :: Developers
Classifier: License :: OSI Approved :: MIT License
Classifier: Operating System :: OS Independent
Classifier: Programming Language :: Python
Classifier: Programming Language :: Python :: 3
Classifier: Programming Language :: Python :: 3.4
Classifier: Programming Language :: Python :: 3.5
Classifier: Programming Language :: Python :: 3.6
Classifier: Topic :: Software Development :: Libraries :: Python Modules
